MANIFEST.in
README.rst
requirements.core.txt
requirements.txt
setup.py
core_custom_queries_app/__init__.py
core_custom_queries_app/admin.py
core_custom_queries_app/apps.py
core_custom_queries_app/exceptions.py
core_custom_queries_app/menus.py
core_custom_queries_app/models.py
core_custom_queries_app/settings.py
core_custom_queries_app/tasks.py
core_custom_queries_app/urls.py
core_custom_queries_app/utils.py
core_custom_queries_app.egg-info/PKG-INFO
core_custom_queries_app.egg-info/SOURCES.txt
core_custom_queries_app.egg-info/dependency_links.txt
core_custom_queries_app.egg-info/requires.txt
core_custom_queries_app.egg-info/top_level.txt
core_custom_queries_app/components/__init__.py
core_custom_queries_app/components/dyn_query/__init__.py
core_custom_queries_app/components/dyn_query/api.py
core_custom_queries_app/components/dyn_query/models.py
core_custom_queries_app/components/dyn_query_step/__init__.py
core_custom_queries_app/components/dyn_query_step/api.py
core_custom_queries_app/components/dyn_query_step/models.py
core_custom_queries_app/components/history_query/__init__.py
core_custom_queries_app/components/history_query/api.py
core_custom_queries_app/components/log_file/__init__.py
core_custom_queries_app/components/log_file/api.py
core_custom_queries_app/components/log_file/models.py
core_custom_queries_app/components/query_to_treat/__init__.py
core_custom_queries_app/components/query_to_treat/api.py
core_custom_queries_app/components/temp_bucket_id_files/__init__.py
core_custom_queries_app/components/temp_bucket_id_files/api.py
core_custom_queries_app/components/temp_bucket_id_files/models.py
core_custom_queries_app/components/temp_bucket_output_file/__init__.py
core_custom_queries_app/components/temp_bucket_output_file/api.py
core_custom_queries_app/components/temp_bucket_output_file/models.py
core_custom_queries_app/components/temp_choice_list_file/__init__.py
core_custom_queries_app/components/temp_choice_list_file/api.py
core_custom_queries_app/components/temp_choice_list_file/models.py
core_custom_queries_app/components/temp_output_file/__init__.py
core_custom_queries_app/components/temp_output_file/api.py
core_custom_queries_app/components/temp_output_file/models.py
