Metadata-Version: 1.0
Name: core-custom-queries-app
Version: 1.0.0b2
Summary: Custom queries app
Home-page: https://github.com/usnistgov/core_custom_queries_app
Author: NIST IT Lab
Author-email: itl_inquiries@nist.gov
License: UNKNOWN
Platform: UNKNOWN
